tiledb_cli/__init__.py
tiledb_cli/cloud.py
tiledb_cli/consolidate_and_vacuum.py
tiledb_cli/convert_from.py
tiledb_cli/dump.py
tiledb_cli/fragments.py
tiledb_cli/root.py
tiledb_cli/utils.py
tiledb_cli/versions.py
tiledb_cli-0.0.5.dist-info/LICENSE
tiledb_cli-0.0.5.dist-info/METADATA
tiledb_cli-0.0.5.dist-info/WHEEL
tiledb_cli-0.0.5.dist-info/entry_points.txt
tiledb_cli-0.0.5.dist-info/top_level.txt
tiledb_cli-0.0.5.dist-info/RECORD
