Metadata-Version: 2.1
Name: tiledb-cli
Version: 0.0.5
Summary: CLI to the TileDB array storage manager
Home-page: https://github.com/TileDB-Inc/TileDB-CLI
Author: TileDB, Inc.
Author-email: help@tiledb.io
Maintainer: TileDB, Inc.
Maintainer-email: help@tiledb.io
License: MIT
Platform: UNKNOWN
Classifier: Development Status :: 4 - Beta
Classifier: Intended Audience :: Developers
Classifier: Intended Audience :: Information Technology
Classifier: Intended Audience :: Science/Research
Classifier: License :: OSI Approved :: MIT License
Classifier: Programming Language :: Python
Classifier: Topic :: Software Development :: Libraries :: Python Modules
Classifier: Operating System :: Unix
Classifier: Operating System :: POSIX :: Linux
Classifier: Operating System :: MacOS :: MacOS X
Classifier: Programming Language :: Python :: 3
Classifier: Programming Language :: Python :: 3.5
Classifier: Programming Language :: Python :: 3.6
Classifier: Programming Language :: Python :: 3.7
Classifier: Programming Language :: Python :: 3.8
Classifier: Programming Language :: Python :: 3.9
License-File: LICENSE
Requires-Dist: click (==7.1.2)
Requires-Dist: setuptools
Requires-Dist: tiledb (>=0.12.0)
Requires-Dist: pandas
Requires-Dist: iso8601
Provides-Extra: ci
Requires-Dist: tiledb-cloud (>=0.7.17) ; extra == 'ci'
Provides-Extra: dev
Requires-Dist: black ; extra == 'dev'
Requires-Dist: cmake (>=3.13) ; extra == 'dev'
Requires-Dist: cython ; extra == 'dev'
Requires-Dist: pybind11 ; extra == 'dev'
Requires-Dist: wheel ; extra == 'dev'
Requires-Dist: setuptools-scm ; extra == 'dev'
Requires-Dist: pytest ; extra == 'dev'
